Metadata-Version: 2.4
Name: neuroops
Version: 0.3.0
Summary: A linter for neuroimaging data + universal format converter to BIDS
Author-email: NeuroOps Team <team@neuroops.io>
License: MIT
Project-URL: Homepage, https://github.com/arthurmoscheni/NeuroGit
Project-URL: Repository, https://github.com/arthurmoscheni/NeuroGit
Project-URL: Issues, https://github.com/arthurmoscheni/NeuroGit/issues
Keywords: neuroimaging,bids,mri,eeg,linter,converter,fmri,nifti
Classifier: Programming Language :: Python :: 3
Classifier: Programming Language :: Python :: 3.8
Classifier: Programming Language :: Python :: 3.9
Classifier: Programming Language :: Python :: 3.10
Classifier: Programming Language :: Python :: 3.11
Classifier: License :: OSI Approved :: MIT License
Classifier: Operating System :: OS Independent
Classifier: Intended Audience :: Science/Research
Classifier: Topic :: Scientific/Engineering :: Medical Science Apps.
Requires-Python: >=3.8
License-File: LICENSE
Requires-Dist: numpy>=1.20.0
Requires-Dist: nibabel>=3.0.0
Requires-Dist: scipy>=1.6.0
Requires-Dist: pydicom>=2.0.0
Provides-Extra: eeg
Requires-Dist: mne>=1.0.0; extra == "eeg"
Provides-Extra: convert
Requires-Dist: mne-bids>=0.12.0; extra == "convert"
Requires-Dist: mne>=1.0.0; extra == "convert"
Provides-Extra: viz
Requires-Dist: streamlit>=1.24.0; extra == "viz"
Requires-Dist: plotly>=5.0.0; extra == "viz"
Requires-Dist: matplotlib>=3.5.0; extra == "viz"
Provides-Extra: all
Requires-Dist: mne>=1.0.0; extra == "all"
Requires-Dist: mne-bids>=0.12.0; extra == "all"
Requires-Dist: streamlit>=1.24.0; extra == "all"
Requires-Dist: plotly>=5.0.0; extra == "all"
Requires-Dist: matplotlib>=3.5.0; extra == "all"
Provides-Extra: dev
Requires-Dist: pytest>=7.0.0; extra == "dev"
Requires-Dist: pytest-cov>=4.0.0; extra == "dev"
Dynamic: license-file
